gamesdb_api/__init__.py
gamesdb_api/constantes.py
gamesdb_api/gamesdb_api.py
gamesdb_api-0.3.5.1.dist-info/LICENSE.txt
gamesdb_api-0.3.5.1.dist-info/METADATA
gamesdb_api-0.3.5.1.dist-info/WHEEL
gamesdb_api-0.3.5.1.dist-info/top_level.txt
gamesdb_api-0.3.5.1.dist-info/RECORD
