Metadata-Version: 2.1
Name: gamesdb-api
Version: 0.3.5.1
Summary: Um pacote Python para extrair informações de jogos do site TheGamesDB.net.
Home-page: UNKNOWN
Author: Bruno Rodrigues
Author-email: email@bruno.gs
License: MIT
Project-URL: GitHub, https://github.com/rc-bruno/gamesdb_api
Platform: UNKNOWN
Classifier: Development Status :: 3 - Alpha
Classifier: Intended Audience :: Developers
Classifier: Natural Language :: Portuguese (Brazilian)
Classifier: License :: OSI Approved :: MIT License
Classifier: Programming Language :: Python :: 3
Classifier: Programming Language :: Python :: 3.6
Classifier: Programming Language :: Python :: 3.7
Classifier: Programming Language :: Python :: 3.8
Classifier: Programming Language :: Python :: 3.9
Classifier: Topic :: Software Development :: Libraries
Classifier: Topic :: Utilities
License-File: LICENSE.txt
Requires-Dist: beautifulsoup4 (==4.11.2)
Requires-Dist: fuzzywuzzy (==0.18.0)
Requires-Dist: Levenshtein (==0.20.9)
Requires-Dist: python-Levenshtein (==0.20.9)
Requires-Dist: requests (==2.28.2)
Requires-Dist: requests-toolbelt (==0.10.1)
Requires-Dist: soupsieve (==2.4)
